[{"__type__":"cc.SpriteFrame","content":{"name":"default_btn_disabled","texture":"71VhFCTINJM6/Ky3oX9nBT","rect":[0,0,40,40],"offset":[0,0],"originalSize":[40,40],"capInsets":[12,12,12,12]}},[{"__type__":"cc.SceneAsset","_name":"aircraft_war_start","scene":{"__id__":1},"asyncLoadAssets":null},{"__type__":"cc.Scene","_name":"New Node","_children":[{"__id__":2},{"__id__":9}],"_anchorPoint":{"__type__":"cc.Vec2"},"_trs":{"__type__":"TypedArray","ctor":"Float64Array","array":[0,0,0,0,0,0,1,1,1,1]},"autoReleaseAssets":true},{"__type__":"cc.Node","_name":"Canvas","_parent":{"__id__":1},"_children":[{"__id__":3},{"__id__":4},{"__id__":5},{"__id__":7},{"__id__":10},{"__id__":12},{"__id__":13}],"_components":[{"__type__":"cc.Canvas","node":{"__id__":2},"_designResolution":{"__type__":"cc.Size","width":375,"height":750}},{"__type__":"cc.Widget","node":{"__id__":2},"_alignFlags":45}],"_color":{"__type__":"cc.Color","r":252,"g":252,"b":252},"_contentSize":{"__type__":"cc.Size","width":375,"height":750},"_trs":{"__type__":"TypedArray","ctor":"Float64Array","array":[187.5,375,0,0,0,0,1,1,1,1]},"_id":"a286bbGknJLZpRpxROV6M94"},{"__type__":"cc.Node","_name":"Main Camera","_parent":{"__id__":2},"_components":[{"__type__":"cc.Camera","node":{"__id__":3},"_clearFlags":7,"_depth":-1}],"_trs":{"__type__":"TypedArray","ctor":"Float64Array","array":[0,0,530.0075471160765,0,0,0,1,1,1,1]}},{"__type__":"cc.Node","_name":"background","_parent":{"__id__":2},"_components":[{"__type__":"cc.Widget","node":{"__id__":4},"alignMode":0,"_alignFlags":45,"_originalWidth":200,"_originalHeight":150}],"_contentSize":{"__type__":"cc.Size","width":375,"height":750},"_trs":{"__type__":"TypedArray","ctor":"Float64Array","array":[0,0,0,0,0,0,1,1,1,1]}},{"__type__":"cc.Node","_name":"loadingMask","_parent":{"__id__":2},"_children":[{"__id__":6}],"_components":[{"__type__":"cc.Widget","node":{"__id__":5},"_alignFlags":45}],"_contentSize":{"__type__":"cc.Size","width":375,"height":750},"_trs":{"__type__":"TypedArray","ctor":"Float64Array","array":[0,0,0,0,0,0,1,1,1,1]}},{"__type__":"cc.Node","_name":"AwMaskbg","_parent":{"__id__":5},"_components":[{"__type__":"cc.Sprite","node":{"__id__":6},"_materials":[{"__uuid__":"ecpdLyjvZBwrvm+cedCcQy"}],"_spriteFrame":{"__uuid__":"b58PO/tPlEUZGMn3JTbO9n"},"_sizeMode":0},{"__type__":"cc.Widget","node":{"__id__":6},"_alignFlags":45,"_originalWidth":100,"_originalHeight":750}],"_opacity":200,"_color":{"__type__":"cc.Color","r":34,"g":34,"b":34},"_contentSize":{"__type__":"cc.Size","width":375,"height":750},"_trs":{"__type__":"TypedArray","ctor":"Float64Array","array":[0,0,0,0,0,0,1,1,1,1]}},{"__type__":"cc.Node","_name":"gameStart","_parent":{"__id__":2},"_children":[{"__id__":8}],"_components":[{"__type__":"cc.Sprite","node":{"__id__":7},"_materials":[{"__uuid__":"ecpdLyjvZBwrvm+cedCcQy"}],"_spriteFrame":{"__uuid__":"b58PO/tPlEUZGMn3JTbO9n"},"_type":1,"_sizeMode":0,"_fillRange":1},{"__type__":"cc.Button","node":{"__id__":7},"zoomScale":0.95,"clickEvents":[{"__type__":"cc.ClickEvent","target":{"__id__":9},"_componentId":"28d22NtPmxBobTFoJ0BfiaM","handler":"startGame"}],"_N$transition":3,"transition":3,"_N$normalColor":{"__type__":"cc.Color","r":196,"g":201,"b":202},"_N$pressedColor":{"__type__":"cc.Color","r":196,"g":201,"b":202},"pressedColor":{"__type__":"cc.Color","r":196,"g":201,"b":202},"_N$hoverColor":{"__type__":"cc.Color","r":196,"g":201,"b":202},"hoverColor":{"__type__":"cc.Color","r":196,"g":201,"b":202},"_N$disabledColor":{"__type__":"cc.Color","r":196,"g":201,"b":202},"_N$pressedSprite":{"__uuid__":"e97GVMl6JHh5Ml5qEDdSGa"},"pressedSprite":{"__uuid__":"e97GVMl6JHh5Ml5qEDdSGa"},"_N$hoverSprite":{"__uuid__":"e97GVMl6JHh5Ml5qEDdSGa"},"hoverSprite":{"__uuid__":"e97GVMl6JHh5Ml5qEDdSGa"},"_N$disabledSprite":{"__uuid__":"29FYIk+N1GYaeWH/q1NxQO"},"_N$target":{"__id__":7}},{"__type__":"cc.Widget","node":{"__id__":7},"alignMode":0,"_alignFlags":17,"_left":205,"_right":235,"_top":300,"_bottom":525,"_originalWidth":200,"_originalHeight":50}],"_color":{"__type__":"cc.Color","r":115,"g":172,"b":184},"_contentSize":{"__type__":"cc.Size","width":150,"height":40},"_trs":{"__type__":"TypedArray","ctor":"Float64Array","array":[0,55,0,0,0,0,1,1,1,1]}},{"__type__":"cc.Node","_name":"Label","_parent":{"__id__":7},"_components":[{"__type__":"cc.Label","node":{"__id__":8},"_materials":[{"__uuid__":"ecpdLyjvZBwrvm+cedCcQy"}],"_useOriginalSize":false,"_string":"START","_N$string":"START","_fontSize":20,"_enableWrapText":false,"_N$file":{"__uuid__":"97fP6bIcdJjrBgVBgAURqL"},"_isSystemFontUsed":false,"_N$horizontalAlign":1,"_N$verticalAlign":1,"_N$overflow":1},{"__type__":"cc.Widget","node":{"__id__":8},"_alignFlags":1}],"_color":{"__type__":"cc.Color","r":245,"g":245,"b":245},"_contentSize":{"__type__":"cc.Size","width":150,"height":40},"_trs":{"__type__":"TypedArray","ctor":"Float64Array","array":[0,0,0,0,0,0,1,1,1,1]}},{"__type__":"cc.Node","_name":"start","_parent":{"__id__":1},"_components":[{"__type__":"28d22NtPmxBobTFoJ0BfiaM","node":{"__id__":9},"loadingBg":{"__id__":6}}],"_trs":{"__type__":"TypedArray","ctor":"Float64Array","array":[187.5,375,0,0,0,0,1,1,1,1]},"_id":"2a752Y9oWFEqbckayRaztqN"},{"__type__":"cc.Node","_name":"back","_parent":{"__id__":2},"_children":[{"__id__":11}],"_components":[{"__type__":"cc.Sprite","node":{"__id__":10},"_materials":[{"__uuid__":"ecpdLyjvZBwrvm+cedCcQy"}],"_spriteFrame":{"__uuid__":"b58PO/tPlEUZGMn3JTbO9n"},"_type":1,"_sizeMode":0},{"__type__":"cc.Button","node":{"__id__":10},"zoomScale":0.95,"clickEvents":[{"__type__":"cc.ClickEvent","target":{"__id__":9},"_componentId":"28d22NtPmxBobTFoJ0BfiaM","handler":"backList"}],"_N$transition":3,"transition":3,"_N$pressedColor":{"__type__":"cc.Color","r":255,"g":255,"b":255},"pressedColor":{"__type__":"cc.Color","r":255,"g":255,"b":255},"_N$disabledColor":{"__type__":"cc.Color","r":255,"g":255,"b":255},"_N$normalSprite":{"__uuid__":"f0BIwQ8D5Ml7nTNQbh1YlS"},"_N$pressedSprite":{"__uuid__":"e97GVMl6JHh5Ml5qEDdSGa"},"pressedSprite":{"__uuid__":"e97GVMl6JHh5Ml5qEDdSGa"},"_N$hoverSprite":{"__uuid__":"e97GVMl6JHh5Ml5qEDdSGa"},"hoverSprite":{"__uuid__":"e97GVMl6JHh5Ml5qEDdSGa"},"_N$disabledSprite":{"__uuid__":"29FYIk+N1GYaeWH/q1NxQO"},"_N$target":{"__id__":10}},{"__type__":"cc.Widget","node":{"__id__":10},"_alignFlags":17,"_right":112.5,"_top":360}],"_color":{"__type__":"cc.Color","r":115,"g":172,"b":184},"_contentSize":{"__type__":"cc.Size","width":150,"height":40},"_trs":{"__type__":"TypedArray","ctor":"Float64Array","array":[0,-5,0,0,0,0,1,1,1,1]}},{"__type__":"cc.Node","_name":"Label","_parent":{"__id__":10},"_components":[{"__type__":"cc.Label","node":{"__id__":11},"_materials":[{"__uuid__":"ecpdLyjvZBwrvm+cedCcQy"}],"_useOriginalSize":false,"_string":"BACK","_N$string":"BACK","_fontSize":20,"_enableWrapText":false,"_N$file":{"__uuid__":"97fP6bIcdJjrBgVBgAURqL"},"_isSystemFontUsed":false,"_N$horizontalAlign":1,"_N$verticalAlign":1,"_N$overflow":1}],"_contentSize":{"__type__":"cc.Size","width":150,"height":40},"_trs":{"__type__":"TypedArray","ctor":"Float64Array","array":[0,0,0,0,0,0,1,1,1,1]}},{"__type__":"cc.Node","_name":"label","_parent":{"__id__":2},"_components":[{"__type__":"cc.Label","node":{"__id__":12},"_materials":[{"__uuid__":"ecpdLyjvZBwrvm+cedCcQy"}],"_useOriginalSize":false,"_string":"AIRCRAFT WAR","_N$string":"AIRCRAFT WAR","_fontSize":28,"_N$file":{"__uuid__":"97fP6bIcdJjrBgVBgAURqL"},"_isSystemFontUsed":false},{"__type__":"cc.Widget","node":{"__id__":12},"_alignFlags":17,"_top":106.66500000000002}],"_color":{"__type__":"cc.Color","r":255,"g":208,"b":109},"_contentSize":{"__type__":"cc.Size","width":213.89,"height":40},"_trs":{"__type__":"TypedArray","ctor":"Float64Array","array":[0,248.33499999999998,0,0,0,0,1,1,1,1]}},{"__type__":"cc.Node","_name":"desc","_parent":{"__id__":2},"_components":[{"__type__":"cc.Label","node":{"__id__":13},"_materials":[{"__uuid__":"ecpdLyjvZBwrvm+cedCcQy"}],"_useOriginalSize":false,"_string":"Left or right sliding control aircraft","_N$string":"Left or right sliding control aircraft","_fontSize":11,"_lineHeight":20,"_N$file":{"__uuid__":"97fP6bIcdJjrBgVBgAURqL"},"_isSystemFontUsed":false,"_N$horizontalAlign":1,"_N$verticalAlign":1},{"__type__":"cc.Widget","node":{"__id__":13},"_alignFlags":12,"_left":10,"_bottom":5}],"_contentSize":{"__type__":"cc.Size","width":175.39,"height":20},"_trs":{"__type__":"TypedArray","ctor":"Float64Array","array":[-89.805,-360,0,0,0,0,1,1,1,1]}}],{"__type__":"cc.SpriteFrame","content":{"name":"mask_bg_ar","texture":"c4Dwdc0c5MjKlJU0zhI3/R","rect":[0,0,4,4],"offset":[0,0],"originalSize":[4,4],"capInsets":[0,0,0,0]}},{"__type__":"cc.SpriteFrame","content":{"name":"default_btn_pressed","texture":"b4P/PCArtIdIH38t6mlw8Y","rect":[0,0,40,40],"offset":[0,0],"originalSize":[40,40],"capInsets":[12,12,12,12]}},{"__type__":"cc.SpriteFrame","content":{"name":"default_btn_normal","texture":"e8Ueib+qJEhL6mXAHdnwbi","rect":[0,0,40,40],"offset":[0,0],"originalSize":[40,40],"capInsets":[12,12,12,12]}}]